Metadata-Version: 2.1
Name: allianceauth-loki-logging
Version: 1.0.0
Summary: A non-blocking django logging handler for Loki
Home-page: https://github.com/Solar-Helix-Independent-Transport/allianceauth-loki-logging
Author: aaronkable
Author-email: aaronkable@gmail.com
License: MIT
Keywords: python,loki,grafana,logging,metrics,threaded
Platform: UNKNOWN
Classifier: License :: OSI Approved :: MIT License
Classifier: Environment :: Web Environment
Classifier: Framework :: Django
Classifier: Programming Language :: Python :: 3.8
Classifier: Programming Language :: Python :: 3.9
Classifier: Programming Language :: Python :: 3.10
License-File: LICENSE
